torrentp/__init__.py
torrentp/cli.py
torrentp/downloader.py
torrentp/session.py
torrentp/torrent_downloader.py
torrentp/torrent_info.py
torrentp-0.2.6.dist-info/licenses/LICENSE
torrentp-0.2.6.dist-info/METADATA
torrentp-0.2.6.dist-info/WHEEL
torrentp-0.2.6.dist-info/entry_points.txt
torrentp-0.2.6.dist-info/top_level.txt
torrentp-0.2.6.dist-info/RECORD
